<PAMDataset>
  <PAMRasterBand band="1">
    <Histograms>
      <HistItem>
        <HistMin>-0.001116721034049988</HistMin>
        <HistMax>2.234558789134026</HistMax>
        <BucketCount>1000</BucketCount>
        <IncludeOutOfRange>0</IncludeOutOfRange>
        <Approximate>0</Approximate>
        <HistCounts>88|0|0|0|0|0|0|0|0|0|0|0|0|0|0|0|0|0|0|0|0|0|0|0|0|0|0|0|0|0|0|0|0|0|0|0|0|0|0|0|0|0|0|0|0|0|0|0|0|0|0|0|0|0|0|0|0|0|0|0|0|0|0|0|0|0|0|0|0|0|0|0|0|0|0|0|0|0|0|0|0|0|0|0|0|0|0|0|0|0|0|0|0|0|0|0|0|0|0|0|0|0|0|0|0|0|0|0|0|0|0|0|0|0|0|0|0|0|0|0|0|0|1|0|0|0|0|0|0|0|0|0|0|0|0|1|0|0|0|0|0|0|0|0|2|0|0|0|0|0|0|0|1|0|0|0|1|0|0|0|0|0|0|0|0|0|0|0|0|0|0|1|0|0|0|0|0|0|0|0|0|0|0|0|0|0|1|0|0|0|0|0|0|0|0|0|0|0|0|0|0|0|0|1|0|0|0|0|0|0|0|0|0|0|0|0|0|0|0|0|0|0|0|0|0|0|0|0|0|0|0|0|0|0|0|0|0|0|0|0|0|0|0|0|0|0|0|1|0|0|0|1|0|1|0|0|0|2|0|0|0|0|0|1|0|0|1|0|0|0|0|0|1|0|0|0|0|0|0|0|0|0|0|1|0|0|0|0|0|0|0|0|1|0|1|2|0|0|0|0|0|0|0|0|0|0|1|0|1|0|0|1|0|1|0|0|0|0|1|0|0|2|0|0|0|0|0|0|0|1|1|0|0|0|2|0|1|0|0|1|0|0|1|0|0|0|1|0|1|0|0|0|1|1|0|1|0|0|1|0|0|1|0|1|0|1|1|1|1|0|0|0|1|1|0|0|0|0|0|0|2|1|0|0|0|0|1|0|1|0|0|0|1|3|0|1|1|1|1|0|0|2|0|2|2|3|2|1|1|1|0|2|1|1|3|2|1|3|0|0|5|1|1|1|2|4|2|3|5|2|0|0|1|3|2|1|1|5|2|0|2|1|1|1|5|1|3|3|2|6|6|3|3|1|4|6|6|2|6|5|4|7|7|3|3|6|7|8|11|0|10|6|5|6|9|9|5|5|7|8|12|10|11|13|12|5|10|12|8|7|11|7|12|14|10|18|13|14|16|10|17|9|13|12|13|10|14|11|19|14|10|11|7|13|15|10|15|11|10|19|11|10|15|12|13|11|7|13|15|14|9|17|13|9|10|8|13|16|10|17|9|12|12|12|9|7|3|12|5|3|7|5|9|5|6|10|12|9|4|8|8|7|4|11|7|6|6|8|10|8|11|11|6|4|8|8|8|6|7|9|7|8|7|7|5|3|14|12|4|8|9|8|8|6|10|11|11|7|8|4|11|10|14|15|14|10|12|10|15|19|16|15|14|15|17|9|20|9|12|8|14|17|13|17|14|11|13|17|14|14|17|12|9|11|15|14|3|12|13|10|10|13|6|4|9|8|5|7|7|9|3|5|3|6|3|5|4|4|2|1|7|0|2|2|4|3|3|0|1|4|0|0|1|2|0|3|0|1|0|2|1|1|4|0|4|1|3|6|3|2|1|3|2|4|2|3|2|3|1|4|2|1|0|0|3|1|2|2|3|0|1|1|3|3|1|0|5|2|3|1|0|1|1|1|1|2|2|0|3|1|1|1|0|2|0|4|3|0|0|2|3|1|2|1|2|1|2|1|0|2|1|4|2|1|0|0|0|0|0|0|1|0|0|2|0|5|1|0|1|2|3|1|0|1|3|1|2|0|0|0|1|1|1|0|1|1|0|0|0|1|0|0|3|1|1|1|1|0|1|0|1|0|0|0|1|1|1|0|0|1|1|0|0|0|0|1|0|1|0|0|0|0|1|0|0|1|1|0|0|0|0|0|0|0|0|0|0|1|0|1|1|0|0|0|1|0|0|0|0|1|0|0|0|1|0|0|0|0|0|0|0|1|0|0|0|0|0|0|0|0|0|0|0|1|0|0|0|1|0|0|1|0|0|0|0|1|0|0|0|1|0|0|0|0|0|1|1|0|0|0|0|0|0|1|0|0|0|0|0|0|0|0|0|0|0|0|0|0|0|0|0|0|0|0|0|0|1|0|0|0|0|0|0|0|0|0|0|0|0|0|0|0|0|0|0|0|1|0|0|0|0|0|1|0|0|0|0|0|0|0|0|0|0|0|0|0|0|0|0|0|0|0|0|0|0|0|0|0|0|0|0|0|0|0|0|0|0|0|0|0|1|0|0|0|0|1|0|0|0|1</HistCounts>
      </HistItem>
    </Histograms>
    <Metadata>
      <MDI key="STATISTICS_MAXIMUM">2.2334420681</MDI>
      <MDI key="STATISTICS_MEAN">1.2142718903928</MDI>
      <MDI key="STATISTICS_MINIMUM">0</MDI>
      <MDI key="STATISTICS_STDDEV">0.3101699046869</MDI>
    </Metadata>
  </PAMRasterBand>
</PAMDataset>
